{"id": "io", "path": "/home/adday/code/cuhackit/code/io.py", "mtime": 1643047078, "size": 65, "hash": "7f19fe0ce8bebb431c81b8a3b1a57a81", "data_mtime": 1643048236, "dependencies": ["builtins", "abc", "typing"], "suppressed": [], "options": {"warn_return_any": false, "disallow_untyped_decorators": false, "local_partial_types": false, "allow_redefinition": false, "disallow_untyped_defs": false, "always_true": [], "disallow_any_expr": false, "strict_optional_whitelist": null, "disallow_untyped_calls": false, "no_implicit_optional": false, "warn_no_return": true, "warn_unreachable": false, "disallow_any_generics": false, "show_none_errors": true, "ignore_errors": false, "disallow_subclassing_any": false, "mypyc": false, "warn_unused_ignores": false, "follow_imports_for_stubs": false, "strict_equality": false, "allow_untyped_globals": false, "disallow_incomplete_defs": false, "follow_imports": "normal", "ignore_missing_imports": false, "plugins": [], "disallow_any_explicit": false, "disallow_any_decorated": false, "strict_optional": true, "platform": "linux", "always_false": [], "check_untyped_defs": false, "bazel": false, "disallow_any_unimported": false, "implicit_reexport": true}, "dep_prios": [5, 30, 30], "dep_lines": [1, 1, 1], "interface_hash": "6f706119205efb148a1843f1f7e04140", "version_id": "0.761", "ignore_all": false, "plugin_data": null}